napari_generic_simulator/Illumination.py
napari_generic_simulator/__init__.py
napari_generic_simulator/_version.py
napari_generic_simulator/_widget.py
napari_generic_simulator/baseSIMulator.py
napari_generic_simulator/napari.yaml
napari_generic_simulator/_tests/__init__.py
napari_generic_simulator/_tests/test_widget.py
napari_generic_SIMulator-0.1.3.dist-info/LICENSE
napari_generic_SIMulator-0.1.3.dist-info/METADATA
napari_generic_SIMulator-0.1.3.dist-info/WHEEL
napari_generic_SIMulator-0.1.3.dist-info/entry_points.txt
napari_generic_SIMulator-0.1.3.dist-info/top_level.txt
napari_generic_SIMulator-0.1.3.dist-info/RECORD
