Metadata-Version: 2.1
Name: napari-generic-SIMulator
Version: 0.1.3
Summary: A napari plugin to simulate raw-image stacks of Structured illumination microscopy (SIM).
Home-page: https://github.com/Meizhu-Liang/napari-generic-SIMulator
Author: Meizhu Liang
Author-email: ml2618@ic.ac.uk
License: BSD-3-Clause
Project-URL: Bug Tracker, https://github.com/Meizhu-Liang/napari-generic-SIMulator/issues
Project-URL: Documentation, https://github.com/Meizhu-Liang/napari-generic-SIMulator#README.md
Project-URL: Source Code, https://github.com/Meizhu-Liang/napari-generic-SIMulator
Project-URL: User Support, https://github.com/Meizhu-Liang/napari-generic-SIMulator/issues
Classifier: Development Status :: 2 - Pre-Alpha
Classifier: Framework :: napari
Classifier: Intended Audience :: Developers
Classifier: License :: OSI Approved :: BSD License
Classifier: Operating System :: OS Independent
Classifier: Programming Language :: Python
Classifier: Programming Language :: Python :: 3
Classifier: Programming Language :: Python :: 3.8
Classifier: Programming Language :: Python :: 3.9
Classifier: Programming Language :: Python :: 3.10
Requires-Python: >=3.8
License-File: LICENSE
Requires-Dist: numpy
Requires-Dist: magicgui
Requires-Dist: qtpy
Requires-Dist: tifffile
Requires-Dist: opt-einsum
Requires-Dist: matplotlib
Requires-Dist: pypcd-imp
Provides-Extra: testing
Requires-Dist: tox; extra == "testing"
Requires-Dist: pytest; extra == "testing"
Requires-Dist: pytest-cov; extra == "testing"
Requires-Dist: pytest-qt; extra == "testing"
Requires-Dist: napari; extra == "testing"
Requires-Dist: pyqt5; extra == "testing"
Requires-Dist: tifffile; extra == "testing"
Requires-Dist: pypcd-imp; extra == "testing"
Requires-Dist: opt-einsum; extra == "testing"
Requires-Dist: matplotlib; extra == "testing"
